odoo/addons/l10n_us_crm_county/README.rst
odoo/addons/l10n_us_crm_county/__init__.py
odoo/addons/l10n_us_crm_county/__manifest__.py
odoo/addons/l10n_us_crm_county/i18n/l10n_us_crm_county.pot
odoo/addons/l10n_us_crm_county/models/__init__.py
odoo/addons/l10n_us_crm_county/models/crm_lead.py
odoo/addons/l10n_us_crm_county/readme/CONTRIBUTORS.md
odoo/addons/l10n_us_crm_county/readme/DESCRIPTION.md
odoo/addons/l10n_us_crm_county/static/description/icon.png
odoo/addons/l10n_us_crm_county/static/description/index.html
odoo/addons/l10n_us_crm_county/tests/__init__.py
odoo/addons/l10n_us_crm_county/tests/test_crm_lead.py
odoo/addons/l10n_us_crm_county/views/crm_lead_views.xml
odoo_addon_l10n_us_crm_county-18.0.0.0.0.2.dist-info/METADATA
odoo_addon_l10n_us_crm_county-18.0.0.0.0.2.dist-info/WHEEL
odoo_addon_l10n_us_crm_county-18.0.0.0.0.2.dist-info/top_level.txt
odoo_addon_l10n_us_crm_county-18.0.0.0.0.2.dist-info/RECORD
