Metadata-Version: 2.1
Name: odoo-addon-l10n_us_crm_county
Version: 18.0.0.0.0.2
Requires-Python: >=3.10
Requires-Dist: odoo-addon-l10n_us_base_county==18.0.*
Requires-Dist: odoo==18.0.*
Summary: Add United States counties to leads.
Home-page: https://github.com/OCA/l10n-usa
License: LGPL-3
Author: MetricWise, Odoo Community Association (OCA)
Author-email: support@odoo-community.org
Classifier: Programming Language :: Python
Classifier: Framework :: Odoo
Classifier: Framework :: Odoo :: 18.0
Classifier: License :: OSI Approved :: GNU Lesser General Public License v3 (LGPLv3)
